warden/HeaderConstruct.py
warden/PackageInfo.py
warden/WardenConfiguration.py
warden/__init__.py
warden/cmd_entry.py
warden/enforce_changelog_content.py
warden/enforce_readme_content.py
warden/enforce_target_file_presence.py
warden/index_packages.py
warden/version.py
warden/warden_common.py
doc_warden-0.7.3.dist-info/METADATA
doc_warden-0.7.3.dist-info/WHEEL
doc_warden-0.7.3.dist-info/entry_points.txt
doc_warden-0.7.3.dist-info/top_level.txt
doc_warden-0.7.3.dist-info/RECORD
