Metadata-Version: 2.4
Name: doc-warden
Version: 0.7.3
Summary: Doc-Warden is an internal project created by the Azure SDK Team. It is intended to be used by CI Builds to ensure that documentation standards are met. See readme for more details.
Home-page: https://github.com/Azure/azure-sdk-tools/
Author: Microsoft Corporation
Author-email: azuresdkengsysadmins@microsoft.com
License: MIT License
Classifier: Development Status :: 3 - Alpha
Classifier: Programming Language :: Python
Classifier: Programming Language :: Python :: 2.7
Classifier: Programming Language :: Python :: 3
Classifier: Programming Language :: Python :: 3.4
Classifier: Programming Language :: Python :: 3.5
Classifier: Programming Language :: Python :: 3.6
Classifier: Programming Language :: Python :: 3.7
Classifier: Programming Language :: Python :: 3.8
Classifier: Programming Language :: Python :: 3.9
Classifier: Programming Language :: Python :: 3.10
Classifier: Programming Language :: Python :: 3.11
Classifier: Programming Language :: Python :: 3.12
Classifier: License :: OSI Approved :: MIT License
Requires-Dist: pyyaml
Requires-Dist: markdown2
Requires-Dist: docutils
Requires-Dist: pygments
Requires-Dist: beautifulsoup4
Requires-Dist: jinja2
Requires-Dist: requests
Requires-Dist: pathlib2
Dynamic: author
Dynamic: author-email
Dynamic: classifier
Dynamic: description
Dynamic: description-content-type
Dynamic: home-page
Dynamic: license
Dynamic: requires-dist
Dynamic: summary
